ideariver_core/__init__.py
ideariver_core/base_plugin.py
ideariver_core/event_message.py
ideariver_core/plugin_metadata.py
ideariver_core/topic_mapping.py
ideariver_core-0.1.6.dist-info/LICENSE
ideariver_core-0.1.6.dist-info/METADATA
ideariver_core-0.1.6.dist-info/WHEEL
ideariver_core-0.1.6.dist-info/top_level.txt
ideariver_core-0.1.6.dist-info/RECORD
