Metadata-Version: 2.1
Name: ideariver_core
Version: 0.1.6
Summary: Core library for ideariver, containing abstract DTOs and interfaces.
Home-page: https://github.com/nima70/ideariver-core-python
Author: ideariver
Author-email: contact@ideariver.com
Classifier: Programming Language :: Python :: 3
Classifier: License :: OSI Approved :: MIT License
Classifier: Operating System :: OS Independent
Requires-Python: >=3.6
License-File: LICENSE
